OptimaLab35/__init__.py
OptimaLab35/__main__.py
OptimaLab35/const.py
OptimaLab35/mainWindow.py
OptimaLab35/previewWindow.py
OptimaLab35/settingsWindow.py
OptimaLab35/ui/__init__.py
OptimaLab35/ui/exif_handler_window.py
OptimaLab35/ui/main_window.py
OptimaLab35/ui/main_window.ui
OptimaLab35/ui/preview_window.py
OptimaLab35/ui/preview_window.ui
OptimaLab35/ui/resources_rc.py
OptimaLab35/ui/settings_window.py
OptimaLab35/ui/settings_window.ui
OptimaLab35/ui/simple_dialog.py
OptimaLab35/utils/__init__.py
OptimaLab35/utils/utility.py
optimalab35-1.8.4.dist-info/METADATA
optimalab35-1.8.4.dist-info/WHEEL
optimalab35-1.8.4.dist-info/entry_points.txt
optimalab35-1.8.4.dist-info/RECORD
