Metadata-Version: 2.4
Name: OptimaLab35
Version: 1.8.4
Summary: User interface for optima35.
Project-URL: Source, https://gitlab.com/CodeByMrFinchum/OptimaLab35
Project-URL: Documentation, https://gitlab.com/CodeByMrFinchum/OptimaLab35/-/blob/main/README.md
Project-URL: Changelog, https://gitlab.com/CodeByMrFinchum/OptimaLab35/-/blob/main/CHANGELOG.md
Author: Mr Finchum
Classifier: Development Status :: 5 - Production/Stable
Classifier: Environment :: X11 Applications :: Qt
Classifier: License :: OSI Approved :: GNU Affero General Public License v3 or later (AGPLv3+)
Classifier: Operating System :: OS Independent
Classifier: Programming Language :: Python :: 3
Classifier: Topic :: Multimedia :: Graphics :: Editors
Requires-Python: <3.14,>=3.9
Requires-Dist: optima35<2.0.0,>=1.0.0
Requires-Dist: pypiupdater<1.0.0,>=0.7.2
Requires-Dist: pyside6
Requires-Dist: pyyaml
